{
"藥品":"Moxifloxacin 口服 400mg/tab (Avelox)",
"學名":"Moxifloxacin",
"商品名":"Avelox",
"學名成份1":"Moxifloxacin 400 mg",
"規格含量":"400mg/tab",
"中文名":"威洛速膜衣錠 (5/片)",
"藥理分類":"[1580] Quinolones",
"健保碼":"BC23223100",
"衛署字號":"衛署藥輸字第023223號",
"廠牌":"Bayer Healthcare Manufacturing S.r.l.(拜耳)",
"產地":"義大利",
"成人劑量":"400 mg PO QD",
"小孩劑量":"Safety and efficacy of oral and IV moxifloxacin have not been established in pediatric patients",
"作用":"抗生素",
"副作用":"失眠、皮疹、光敏感、陰道有分泌物及疼痛、虛弱、暈眩、腹痛、腹瀉、噁心、頭痛",
"儲存條件":"小於 30°C儲存",
"用法":"口服",
"用藥指導":"與鐵劑,制酸劑至少錯開兩小時服用",
"注意事項":"1、口服劑型與含有Mg2+、AL3+之制酸劑或多價陽離子製劑(Fe2+、Zn2+)併用時，會導致吸收低下，效果減弱，請避免併用。\n2、Moxifloxacin使用於<18歲族群之安全性尚未確立，動物研究觀察到Moxifloxacin 會造成未成年動物關節病變，十八歲以下不建議使用。\n3、Moxifloxacin與cisapride、erythromycin、antipsychotics、tricyclic antidepressants、procainamide、quinidine、amiodarone、sotalol併用可能會延長QT間隔，故不建議併用，"
}